onboardapis/__init__.py
onboardapis/data.py
onboardapis/exceptions.py
onboardapis/mixins.py
onboardapis/protocols.py
onboardapis/py.typed
onboardapis/units.py
onboardapis/bus/__init__.py
onboardapis/other/NAMESPACE.txt
onboardapis/plane/__init__.py
onboardapis/plane/cz/__init__.py
onboardapis/plane/cz/tvl.py
onboardapis/plane/cz/tvp.py
onboardapis/plane/cz/tvq.py
onboardapis/plane/cz/tvs.py
onboardapis/plane/de/__init__.py
onboardapis/plane/de/cib.py
onboardapis/plane/de/cfg/__init__.py
onboardapis/plane/de/cfg/apis.py
onboardapis/plane/de/cfg/interfaces.py
onboardapis/plane/ee/__init__.py
onboardapis/plane/ee/mbu.py
onboardapis/plane/no/__init__.py
onboardapis/plane/no/wif.py
onboardapis/plane/third_party/__init__.py
onboardapis/plane/third_party/betria_interactive/__init__.py
onboardapis/plane/third_party/betria_interactive/apis.py
onboardapis/plane/third_party/betria_interactive/interfaces.py
onboardapis/plane/third_party/inflight_dublin/__init__.py
onboardapis/plane/third_party/inflight_dublin/apis.py
onboardapis/ship/__init__.py
onboardapis/train/__init__.py
onboardapis/train/at/__init__.py
onboardapis/train/at/obb/__init__.py
onboardapis/train/at/obb/apis.py
onboardapis/train/at/obb/interfaces.py
onboardapis/train/cz/__init__.py
onboardapis/train/cz/cd/__init__.py
onboardapis/train/cz/cd/apis.py
onboardapis/train/cz/cd/interfaces.py
onboardapis/train/cz/cd/schema.py
onboardapis/train/de/__init__.py
onboardapis/train/de/bth/__init__.py
onboardapis/train/de/db/__init__.py
onboardapis/train/de/db/apis.py
onboardapis/train/de/db/interfaces.py
onboardapis/train/de/db/mappings.yaml
onboardapis/train/de/flix/__init__.py
onboardapis/train/de/flix/apis.py
onboardapis/train/de/flix/interfaces.py
onboardapis/train/de/me/__init__.py
onboardapis/train/de/me/apis.py
onboardapis/train/de/me/interfaces.py
onboardapis/train/de/tdh/__init__.py
onboardapis/train/de/tdh/apis.py
onboardapis/train/fr/__init__.py
onboardapis/train/fr/sncf/__init__.py
onboardapis-2.1.0.dist-info/licenses/LICENSE
onboardapis-2.1.0.dist-info/METADATA
onboardapis-2.1.0.dist-info/WHEEL
onboardapis-2.1.0.dist-info/top_level.txt
onboardapis-2.1.0.dist-info/RECORD
