Metadata-Version: 2.4
Name: onboardapis
Version: 2.1.0
Summary: A pure Python wrapper for the on-board APIs of many different transportation providers.
Author-email: Felix Zenk <felix.zenk@web.de>
License-Expression: MIT
Project-URL: Homepage, https://felix-zenk.github.io/onboardapis
Project-URL: Documentation, https://felix-zenk.github.io/onboardapis/
Project-URL: Repository, https://github.com/felix-zenk/onboardapis
Project-URL: Issues, https://github.com/felix-zenk/onboardapis/issues
Keywords: public-transport,train,api
Classifier: Operating System :: OS Independent
Classifier: Programming Language :: Python :: 3
Classifier: Programming Language :: Python :: 3.8
Classifier: Programming Language :: Python :: 3.9
Classifier: Programming Language :: Python :: 3.10
Classifier: Programming Language :: Python :: 3.11
Classifier: Programming Language :: Python :: 3.12
Classifier: Programming Language :: Python :: 3.13
Classifier: Topic :: Utilities
Classifier: Topic :: Internet :: WWW/HTTP :: Dynamic Content
Classifier: Typing :: Typed
Requires-Python: >=3.9
License-File: LICENSE
Requires-Dist: annotated-types>=0.7.0
Requires-Dist: beautifulsoup4>=4.14.2
Requires-Dist: geopy>=2.4.1
Requires-Dist: gql[all]>=4.0.0
Requires-Dist: requests>=2.32.5
Requires-Dist: restfly>=1.5.1
Requires-Dist: PyYAML>=6.0.3
Provides-Extra: dev
Requires-Dist: build>=1.2.2.post1; extra == "dev"
Requires-Dist: flake8>=7.2.0; extra == "dev"
Requires-Dist: Flake8-pyproject>=1.2.3; extra == "dev"
Requires-Dist: pdoc>=15.0.4; extra == "dev"
Requires-Dist: pytest>=8.4.0; extra == "dev"
Requires-Dist: pytest-cov>=6.1.1; extra == "dev"
Dynamic: license-file
